lndgrpc/__init__.py
lndgrpc/__main__.py
lndgrpc/aio/__init__.py
lndgrpc/aio/async_client.py
lndgrpc/client.py
lndgrpc/common.py
lndgrpc/compiled/autopilot.proto
lndgrpc/compiled/autopilot_pb2.py
lndgrpc/compiled/autopilot_pb2_grpc.py
lndgrpc/compiled/chainnotifier.proto
lndgrpc/compiled/chainnotifier_pb2.py
lndgrpc/compiled/chainnotifier_pb2_grpc.py
lndgrpc/compiled/invoices.proto
lndgrpc/compiled/invoices_pb2.py
lndgrpc/compiled/invoices_pb2_grpc.py
lndgrpc/compiled/lncli.proto
lndgrpc/compiled/lncli_pb2.py
lndgrpc/compiled/lncli_pb2_grpc.py
lndgrpc/compiled/router.proto
lndgrpc/compiled/router_pb2.py
lndgrpc/compiled/router_pb2_grpc.py
lndgrpc/compiled/rpc.proto
lndgrpc/compiled/rpc_pb2.py
lndgrpc/compiled/rpc_pb2_grpc.py
lndgrpc/compiled/signer.proto
lndgrpc/compiled/signer_pb2.py
lndgrpc/compiled/signer_pb2_grpc.py
lndgrpc/compiled/stateservice.proto
lndgrpc/compiled/stateservice_pb2.py
lndgrpc/compiled/stateservice_pb2_grpc.py
lndgrpc/compiled/verrpc.proto
lndgrpc/compiled/verrpc_pb2.py
lndgrpc/compiled/verrpc_pb2_grpc.py
lndgrpc/compiled/walletkit.proto
lndgrpc/compiled/walletkit_pb2.py
lndgrpc/compiled/walletkit_pb2_grpc.py
lndgrpc/compiled/walletunlocker.proto
lndgrpc/compiled/walletunlocker_pb2.py
lndgrpc/compiled/walletunlocker_pb2_grpc.py
lndgrpc/compiled/watchtower.proto
lndgrpc/compiled/watchtower_pb2.py
lndgrpc/compiled/watchtower_pb2_grpc.py
lndgrpc/compiled/wtclient.proto
lndgrpc/compiled/wtclient_pb2.py
lndgrpc/compiled/wtclient_pb2_grpc.py
lndgrpc/errors.py
py_lnd_grpc-0.3.7.dist-info/LICENSE
py_lnd_grpc-0.3.7.dist-info/WHEEL
py_lnd_grpc-0.3.7.dist-info/METADATA
py_lnd_grpc-0.3.7.dist-info/RECORD
